GenMRMR.py
genmrmr-0.1.0.dist-info/METADATA
genmrmr-0.1.0.dist-info/WHEEL
genmrmr-0.1.0.dist-info/RECORD
