Metadata-Version: 2.1
Name: genmrmr
Version: 0.1.0
Summary: Algorithm that uses genetic and MRMR for feature selection
Author: Maksim Tislenko
Requires-Python: >=3.10,<4.0
Classifier: Programming Language :: Python :: 3
Classifier: Programming Language :: Python :: 3.10
Classifier: Programming Language :: Python :: 3.11
Requires-Dist: dask (==2022.11.1)
Requires-Dist: imbalanced-learn (==0.9.1)
Requires-Dist: imblearn (==0.0)
Requires-Dist: itmo-fs (==0.3.3)
Requires-Dist: numpy (==1.23.5)
Requires-Dist: scikit-learn (==1.1.3)
